acpoa/__init__.py
acpoa/cli.py
acpoa/configuration.py
acpoa/core.py
acpoa/hookshandler.py
acpoa/plugin_base.py
acpoa/plugin_manager.py
acpoa/repository_manager.py
acpoa/singleton.py
acpoa-0.0.7.dist-info/LICENSE
acpoa-0.0.7.dist-info/METADATA
acpoa-0.0.7.dist-info/WHEEL
acpoa-0.0.7.dist-info/top_level.txt
acpoa-0.0.7.dist-info/RECORD
