Metadata-Version: 2.1
Name: acpoa
Version: 0.0.7
Summary: Application Core for Plugin Oriented Applications
Home-page: https://github.com/Leikt/acpoa-core
Author: Leikt
Author-email: leikt.solreihin@gmail.com
License: UNKNOWN
Project-URL: Bug Tracker, https://github.com/Leikt/acpoa-core/issues
Project-URL: Wiki, https://github.com/Leikt/acpoa-core/wiki
Project-URL: Discussions, https://github.com/Leikt/acpoa-core/discussions
Platform: UNKNOWN
Classifier: Programming Language :: Python :: 3
Classifier: License :: OSI Approved :: MIT License
Classifier: Operating System :: OS Independent
Requires-Python: >=3.9
License-File: LICENSE
Requires-Dist: requests
